{
  "segments": {
    "git": {
      "enabled": true,
      "showSha": false
    },
    "subscription": {
      "enabled": true,
      "showPercentage": true,
      "showTokens": true
    },
    "context": {
      "enabled": true
    },
    "burnRate": {
      "enabled": true
    },
    "timeLeft": {
      "enabled": false
    }
  },
  "format": {
    "separator": " ",
    "icons": {
      "git": "⑂",
      "subscription": "↻",
      "context": "◐",
      "burnRate": "✽",
      "timeLeft": "⏱"
    }
  },
  "colors": {
    "safe": "#00ff00",
    "warning": "#ffff00", 
    "critical": "#ff0000",
    "neutral": "#888888"
  },
  "thresholds": {
    "warning": 80,
    "critical": 100
  }
}